minik/__init__.py
minik/builders.py
minik/constants.py
minik/core.py
minik/exceptions.py
minik/fields.py
minik/middleware.py
minik/models.py
minik/router.py
minik/status_codes.py
minik/structures.py
minik/utils.py
minik-0.5.8.dist-info/AUTHORS
minik-0.5.8.dist-info/LICENSE
minik-0.5.8.dist-info/METADATA
minik-0.5.8.dist-info/WHEEL
minik-0.5.8.dist-info/top_level.txt
minik-0.5.8.dist-info/RECORD
