Metadata-Version: 2.1
Name: minik
Version: 0.5.8
Summary: Web framework for the serverless domain
Home-page: https://github.com/eabglobal/minik
Author: EAB tech
Author-email: opensource@eab.com
License: Apache Software License
Project-URL: Code, https://github.com/eabglobal/minik
Project-URL: Issue tracker, https://github.com/eabglobal/minik/issues
Platform: UNKNOWN
Classifier: Environment :: Web Environment
Classifier: Intended Audience :: Developers
Classifier: License :: OSI Approved :: Apache Software License
Classifier: Operating System :: OS Independent
Classifier: Programming Language :: Python
Classifier: Programming Language :: Python :: 3.5
Classifier: Programming Language :: Python :: 3.6
Classifier: Programming Language :: Python :: 3.7
Classifier: Topic :: Software Development :: Libraries :: Python Modules
